simpletkinter/__init__.py
simpletkinter/_version.py
simpletkinter/src/__init__.py
simpletkinter/src/tkframes.py
simpletkinter/src/tkwidgets.py
simpletkinter-0.0.6.dist-info/LICENSE.txt
simpletkinter-0.0.6.dist-info/METADATA
simpletkinter-0.0.6.dist-info/WHEEL
simpletkinter-0.0.6.dist-info/top_level.txt
simpletkinter-0.0.6.dist-info/RECORD
