Metadata-Version: 2.1
Name: simpletkinter
Version: 0.0.6
Summary: """A utility creating and displaying tkinter widgets."""
Home-page: https://psionman@bitbucket.org/psionman/bfgdealer.git
Download-URL: https://pypi.org/project/bfgdealer/
Author: jeff watkins
Author-email: support@bidforgame.com
License: MIT
Keywords: cli,input
License-File: LICENSE.txt
